pulse_mantine/__init__.py
pulse_mantine/__init__.pyi
pulse_mantine/charts/__init__.py
pulse_mantine/charts/area_chart.py
pulse_mantine/charts/bar_chart.py
pulse_mantine/charts/bubble_chart.py
pulse_mantine/charts/chart_legend.py
pulse_mantine/charts/chart_tooltip.py
pulse_mantine/charts/composite_chart.py
pulse_mantine/charts/donut_chart.py
pulse_mantine/charts/funnel_chart.py
pulse_mantine/charts/heatmap.py
pulse_mantine/charts/line_chart.py
pulse_mantine/charts/pie_chart.py
pulse_mantine/charts/radar_chart.py
pulse_mantine/charts/radial_bar_chart.py
pulse_mantine/charts/scatter_chart.py
pulse_mantine/charts/sparkline.py
pulse_mantine/core/__init__.py
pulse_mantine/core/base.py
pulse_mantine/core/box.py
pulse_mantine/core/buttons/__init__.py
pulse_mantine/core/buttons/action_icon.py
pulse_mantine/core/buttons/button.py
pulse_mantine/core/buttons/close_button.py
pulse_mantine/core/buttons/copy_button.py
pulse_mantine/core/buttons/file_button.py
pulse_mantine/core/buttons/unstyled_button.py
pulse_mantine/core/combobox/__init__.py
pulse_mantine/core/combobox/autocomplete.py
pulse_mantine/core/combobox/combobox.py
pulse_mantine/core/combobox/multi_select.py
pulse_mantine/core/combobox/pill.py
pulse_mantine/core/combobox/pills_input.py
pulse_mantine/core/combobox/select.py
pulse_mantine/core/combobox/tags_input.py
pulse_mantine/core/data_display/__init__.py
pulse_mantine/core/data_display/accordion.py
pulse_mantine/core/data_display/avatar.py
pulse_mantine/core/data_display/background_image.py
pulse_mantine/core/data_display/badge.py
pulse_mantine/core/data_display/card.py
pulse_mantine/core/data_display/color_swatch.py
pulse_mantine/core/data_display/image.py
pulse_mantine/core/data_display/indicator.py
pulse_mantine/core/data_display/kbd.py
pulse_mantine/core/data_display/number_formatter.py
pulse_mantine/core/data_display/spoiler.py
pulse_mantine/core/data_display/theme_icon.py
pulse_mantine/core/data_display/timeline.py
pulse_mantine/core/feedback/__init__.py
pulse_mantine-0.1.29.dist-info/WHEEL
pulse_mantine-0.1.29.dist-info/METADATA
pulse_mantine-0.1.29.dist-info/RECORD
