Metadata-Version: 2.3
Name: pulse-mantine
Version: 0.1.29
Summary: Add your description here
Author: Erwin Kuhn
Author-email: Erwin Kuhn <erwin.kuhn@protonmail.com>
Requires-Dist: pulse-framework>=0.1.18
Requires-Python: >=3.12
